nia/__init__.py
nia_tb-0.0.1.dist-info/LICENSE
nia_tb-0.0.1.dist-info/METADATA
nia_tb-0.0.1.dist-info/WHEEL
nia_tb-0.0.1.dist-info/top_level.txt
nia_tb-0.0.1.dist-info/RECORD
