Metadata-Version: 2.1
Name: nia-tb
Version: 0.0.1
Summary: NeuroImaging Analysis ToolBox
Author-email: Ma Feilong <mafeilong@gmail.com>
License: BSD 3-Clause License        
Project-URL: Homepage, https://github.com/feilong/nia-tb
Project-URL: Bug Tracker, https://github.com/feilong/nia-tb/issues
Classifier: Programming Language :: Python :: 3
Classifier: Programming Language :: Python :: 3 :: Only
Classifier: License :: OSI Approved :: BSD License
Classifier: Operating System :: OS Independent
Classifier: Intended Audience :: Science/Research
Classifier: Topic :: Scientific/Engineering
Requires-Python: >=3.6
License-File: LICENSE
Requires-Dist: numpy
